energymeter.py
energymeter-1.3.0.dist-info/METADATA
energymeter-1.3.0.dist-info/WHEEL
energymeter-1.3.0.dist-info/top_level.txt
energymeter-1.3.0.dist-info/RECORD
