Metadata-Version: 2.1
Name: energymeter
Version: 1.3.0
Summary: A Python module for interfacing with several energy meters
Author-email: ElaadNL <developers@elaad.nl>, Stan Janssen <stanjanssen@finetuned.nl>
License: Apache License, Version 2.0
Project-URL: repository, https://github.com/ElaadNL/python-energymeter.git
Keywords: Energy meter,Modbus
Classifier: Development Status :: 4 - Beta
Classifier: Programming Language :: Python
Requires-Python: >=3.3
Requires-Dist: pyserial
Requires-Dist: minimalmodbus (~=2.0)
Requires-Dist: tinysbus
